README.md
setup.py
flask_json_pattern/__init__.py
flask_json_pattern/_version.py
flask_json_pattern/json_pattern.py
flask_json_pattern/validator.py
flask_json_pattern.egg-info/PKG-INFO
flask_json_pattern.egg-info/SOURCES.txt
flask_json_pattern.egg-info/dependency_links.txt
flask_json_pattern.egg-info/requires.txt
flask_json_pattern.egg-info/top_level.txt