Metadata-Version: 2.1
Name: flask-json-pattern
Version: 0.0.2
Summary: UNKNOWN
Home-page: https://github.com/jeffaguilar08/flask-json-pattern
Author: Jeff Aguilar
Author-email: jeff.aguilar.06@gmail.com
License: MIT
Download-URL: https://github.com/jeffaguilar08/flask-json-pattern.git
Keywords: flask,json,validation,schema,jsonschema,jsonpattern
Platform: UNKNOWN
Classifier: Development Status :: 3 - Alpha
Classifier: Intended Audience :: Developers
Classifier: Topic :: Software Development :: Build Tools
Classifier: License :: OSI Approved :: MIT License
Classifier: Programming Language :: Python :: 3.6
Classifier: Programming Language :: Python :: 3.7
Classifier: Programming Language :: Python :: 3.8
Classifier: Programming Language :: Python :: 3.9
